src/ALU.v
module ALU(
    input [7:0] A,
    input [7:0] B,
    input [2:0] alu_op,
    output reg [7:0] out_put,
    output zero,
    output overflow,
    output carry
);
   reg [8:0] temp_out;
   assign zero = (out_put == 8'b0);
   assign carry = temp_out[8];
   assign overflow = (alu_op == 3'b000)? (A[7]&B[7]&~(out_put[7])|~(A[7])&~(B[7])&out_put[7]):
                     (alu_op == 3'b001)? (A[7]&~(B[7])&~(out_put[7])|~(A[7])&B[7]&out_put[7]):
                     1'b0;
   always @(*) begin 
        
        temp_out = 9'b0;
        case (alu_op)
        //addition
        3'b000: begin 
            temp_out = A + B;
            out_put = temp_out[7:0];
        end
        //subtraction
        3'b001: begin
            temp_out = A - B;
            out_put = temp_out[7:0];
        end
        //logical operations
        3'b010: out_put = A & B;
        3'b011: out_put = A | B;
        3'b100: out_put = A ^ B;
        //MOV
        3'b101: out_put = B;//
        3'b110: out_put = 8'b0;
        3'b111: out_put = 8'b0;
        default : out_put = 8'b0;
        endcase
   end                 
   
endmodule

src/register_file.v
module register_file ( 
    input clk,
    input we,
    input [2:0]rs,
    input [2:0]rt,
    input [2:0]rd,
    input [7:0]wd,
    output [7:0]rd1,
    output [7:0]rd2
);

integer i;
reg [7:0] registers [0:7];


//assigning register to rd1 and rd2
assign rd1 = registers[rs];
assign rd2 = registers[rt];



always @(posedge clk) begin
    if (we) begin
        registers[rd] <= wd;
    end
end


initial begin
    for(i = 0; i < 8; i = i + 1) begin
        registers[i] = 8'b0;
    end
end
endmodule

src/datapath.v
module datapath(
        input clk,
        input [5:0] immidiate,
        input select_imm,
        input [2:0] rs, rt, rd, alu_op,
        input reg_write,
        output carry,
        output overflow,
        output zero
);



wire [7:0] x;
reg [7:0] y;
wire [7:0] z;
reg [7:0] immidiate_8;
wire [7:0] w;
wire alu_carry, alu_overflow, alu_zero;

assign carry = alu_carry;
assign overflow = alu_overflow;
assign zero = alu_zero;
always @(*) begin
    case(immidiate[5])
        1'b0 : immidiate_8 = { 2'b0 , immidiate};
        1'b1 : immidiate_8 = {3'b100 , immidiate[4:0]};
    endcase
end

always @(*) begin
    case(select_imm)
        1'b0: y = w;
        1'b1: y = immidiate_8;
    endcase
end

register_file rf(
    .clk(clk),
    .we(reg_write),
    .rs(rs),
    .rt(rt),
    .rd(rd),
    .wd(z),
    .rd1(x),
    .rd2(w)
);

ALU al(
    .A(x),
    .B(y),
    .out_put(z),
    .carry(alu_carry),
    .overflow(alu_overflow),
    .zero(alu_zero),
    .alu_op(alu_op)
);

endmodule

src/control_unit.v
module control_unit(
    input [15:0] instruction,
    output [2:0] rd,
    output [2:0] rs,
    output [2:0] rt,
    output [5:0] immidiate,
    output reg reg_write,
    output reg [2:0] alu_op,
    output reg branch,
    output reg select_imm
    );

    wire [3:0] opcode;
    assign opcode = instruction[15:12];
    assign rd = instruction[11:9];
    assign rs = instruction[8:6];
    assign rt = instruction[5:3];
    assign immidiate = instruction[5:0];

    always @(*) begin
        alu_op = 3'b0;
        reg_write = 1'b0;
        select_imm = 1'b0;
        branch = 1'b0;
        
        case(opcode)
    // R type instruction
    4'b0000 : begin// addition
        alu_op = 3'b000;
        select_imm = 1'b0;
        reg_write = 1'b1;
    end

    4'b0001 : begin// subtraction
        alu_op = 3'b001;
        select_imm = 1'b0;
        reg_write = 1'b1;
    end

    4'b0010 : begin // and
        alu_op = 3'b010;
        select_imm = 1'b0;
        reg_write = 1'b1;
    end

    4'b0011 : begin // or
        alu_op = 3'b011;
        select_imm = 1'b0;
        reg_write = 1'b1;
    end

    4'b0100 : begin // exor
        alu_op = 3'b100;
        select_imm = 1'b0;
        reg_write = 1'b1;
    end

    4'b0101 : begin // move
        alu_op = 3'b101;
        select_imm = 1'b0;
        reg_write = 1'b1;
    end

    4'b0110 : begin // for future
        alu_op = 3'b110;
        select_imm = 1'b0;
        reg_write = 1'b1;
    end

    4'b0111 : begin // for future
        alu_op = 3'b111;
        select_imm = 1'b0;
        reg_write = 1'b1;
    end

    // I type instructoin

    4'b1000 : begin// addition
        alu_op = 3'b000;
        select_imm = 1'b1;
        reg_write = 1'b1;
    end

    4'b1001 : begin// sub
        alu_op = 3'b001;
        select_imm = 1'b1;
        reg_write = 1'b1;
    end

    4'b1010 : begin//and
        alu_op = 3'b010;
        select_imm = 1'b1;
        reg_write = 1'b1;
    end

    4'b1011 : begin//or
        alu_op = 3'b011;
        select_imm = 1'b1;
        reg_write = 1'b1;
    end

    4'b1100 : begin//exor
        alu_op = 3'b100;
        select_imm = 1'b1;
        reg_write = 1'b1;
    end

    4'b1101 : begin//move
        alu_op = 3'b101;
        select_imm = 1'b1;
        reg_write = 1'b1;
    end

    4'b1111 : begin //future use
        alu_op = 3'b000;
        select_imm = 1'b1;
        reg_write = 1'b1;
    end
    
    4'b1110 : begin // branch if equal
        alu_op = 3'b001; // subtraction
        select_imm = 1'b1;
        reg_write = 1'b0;
        branch = 1'b1;
    end
        endcase
    end
endmodule

src/instruction_mem.v
//instruction memory module with 16 bit instruction but size of the memory address is 8 bit 
module instruction_mem(
    input [7:0] address,
    output [15:0] instruction
);
reg [7:0] memory [0:255]; //memor location has 256 addresses and each address has 8 bit data 
assign instruction = {memory[address],memory[address+1]};//concatenating two 8 bit instruction to make a 16 bit instruction
//one memory locattion has 8 bit data so the entire instruction is stored in two memory locations add and add + 1
initial begin
    //example instructions to be stored in instruction memory
    memory[0] = 8'b00000001; // first 8 bits of instruction 1
    memory[1] = 8'b00011000; // last 8 bits of instruction 1
    memory[2] = 8'b00010010; // first 8 bits of instruction 2
    memory[3] = 8'b00100100; // last 8 bits of instruction 2
    // Add more instructions as needed
end 



endmodule

src/program_counter.v
//program counter module
module program_counter (
    input wire clk,
    //Restarts program from address 0
    input wire reset,
    //this is control signal related to the branch instruction
    input wire branch,
    //when the register value is zero after the alu operation which basically means the value of R1 and R2 are same 
    input wire zero,
    //branch offset SIGNED
    //What is branch offset?
    // making decisions based on the conditions 
    input wire [5:0] immidiate,
    output reg [7:0] PC
);
wire branch_should_happen;
wire [7:0] PC_next;
reg [7:0] branch_offset;
//extending the six bits to 8 bits 
always @(*) begin
    case(immidiate[5])
        1'b0 : branch_offset = { 2'b0 , immidiate};
        1'b1 : branch_offset = {3'b100 , immidiate[4:0]};
    endcase
end
wire [7:0] PC_branch_address;
assign branch_should_happen = branch & zero;
//both conditions should be met for branch to happen
assign PC_next = PC + 2;
assign PC_branch_address = PC + branch_offset + branch_offset;//since each instruction is of two bytes
always @(posedge clk) begin
    if (reset)
    PC <= 8'b0;//Reset : go to the sddress 0
    else if (branch_should_happen)
    PC <= PC_branch_address;//jumping to target address
    else
    PC <= PC_next;//normal opertation as usual PC + 1
end


endmodule

src/top_cpu.v
module top_cpu(
    input wire clk,
    input wire reset
);
//Program counter wires
wire [7:0] PC;
//instruction memory wires
wire [15:0] instruction;
//control signals
wire branch, zero;
wire [5:0] immidiate;
//linking program counter and instruction memory
program_counter PC_instr(
    .clk(clk),
    .reset(reset),
    .PC(PC),
    .branch(branch),//i think it will be connected according to the signal 
    .zero(zero),//i think it will be connected according to the signal
    .immidiate(immidiate)//i think it will be connected according to the signal
);
instruction_mem instruction_memory(
    .address(PC),
    .instruction(instruction)
);
//instruction decode wires
wire [3:0] opcode;
wire [2:0] rd, rs, rt, alu_op;
wire select_imm, we;
control_unit cu(
    .instruction(instruction),
    .rd(rd),
    .rs(rs),
    .rt(rt),
    .immidiate(immidiate),
    .reg_write(we),//lets see later
    .alu_op(alu_op),//lets see later
    .select_imm(select_imm)//lets see later
);
datapath dp(
    .clk(clk),
    .immidiate(immidiate),
    .select_imm(select_imm),
    .rs(rs),
    .rt(rt),
    .rd(rd),
    .alu_op(alu_op),
    .reg_write(we),
    .carry(carry),
    .overflow(overflow),
    .zero(zero)
);

endmodule

testbench/testbench5.v
`timescale 1ns/1ps
module tb_cpu2;
reg clk;
reg reset;
//instantiate the cpu
top_cpu cpu(
    .clk(clk),
    .reset(reset)
);
//clock generation
initial begin
    clk = 0;
    forever #10 clk = ~clk; //toggles after every 10 ns
end
//loading a program into the instruction memory
initial begin
    //LI R1, 30: opcode=1111, rd=001, imm=011110
    cpu.instruction_memory.memory[0] = 8'b11110010; // upper 8 bits: 1111 0010
    cpu.instruction_memory.memory[1] = 8'b00011110; // lower 8 bits: 0010 1000
    //LI R2, 20: opcode=1111, rd=010, imm=010100
    cpu.instruction_memory.memory[2] = 8'b11110100; // upper 8 bits: 1111 0100
    cpu.instruction_memory.memory[3] = 8'b00010100; // lower 8 bits: 0100 0000
    //ADD R3, R1, R2: opcode=0000, rd=011, rs=001, rt=010
    cpu.instruction_memory.memory[4] = 8'b00000110; // upper 8 bits: 0000 0110
    cpu.instruction_memory.memory[5] = 8'b01010000; // lower 8 bits: 0101 0000
    //sub R4, R1, R2: opcode=0001, rd=100, rs=001, rt=010
    cpu.instruction_memory.memory[6] = 8'b00011000; // upper 8 bits: 0001 1000
    cpu.instruction_memory.memory[7] = 8'b01010000; // lower 8 bits: 0101 0000
end
//reset
initial begin
    $display("\n====CPU simulation started====\n");
    reset = 1;
    $display("Time = %0t : Reset asserted",$time);
    #40 reset = 0;
    $display("Time = %0t : Reset desserted, CPU running\n",$time);
    #20
    $display("Time = %0t : R1 = %d",$time, cpu.dp.rf.registers[1]);
    #20
    $display("Time = %0t : R2 = %d",$time, cpu.dp.rf.registers[2]);
    #20
    $display("Time = %0t : R3 = %d",$time, cpu.dp.rf.registers[3]);
    #20
    $display("Time = %0t : R4 = %d",$time, cpu.dp.rf.registers[4]);
    #100
    // Final register values
    $display("\n====Final results====\n");
    $display("R1 = %d",cpu.dp.rf.registers[1]);
    $display("R2 = %d",cpu.dp.rf.registers[2]);
    $display("R3 = %d",cpu.dp.rf.registers[3]);
    $display("R4 = %d",cpu.dp.rf.registers[4]);
    $display("\n===Simulation completed===\n");
    #200 $finish;
end
//VCD dump
initial begin
    $dumpfile("tb_cpu2.vcd");
    $dumpvars(0, tb_cpu2);
end

endmodule

tb_cpu2.vcd
$date
	Sat Feb 14 06:46:09 2026
$end
$version
	Icarus Verilog
$end
$timescale
	1ps
$end
$scope module tb_cpu2 $end
$var reg 1 ! clk $end
$var reg 1 " reset $end
$scope module cpu $end
$var wire 1 # branch $end
$var wire 1 ! clk $end
$var wire 1 " reset $end
$var wire 1 $ zero $end
$var wire 1 % we $end
$var wire 1 & select_imm $end
$var wire 3 ' rt [2:0] $end
$var wire 3 ( rs [2:0] $end
$var wire 3 ) rd [2:0] $end
$var wire 1 * overflow $end
$var wire 16 + instruction [15:0] $end
$var wire 6 , immidiate [5:0] $end
$var wire 1 - carry $end
$var wire 3 . alu_op [2:0] $end
$var wire 8 / PC [7:0] $end
$scope module PC_instr $end
$var wire 1 # branch $end
$var wire 1 0 branch_should_happen $end
$var wire 1 ! clk $end
$var wire 1 " reset $end
$var wire 1 $ zero $end
$var wire 6 1 immidiate [5:0] $end
$var wire 8 2 PC_next [7:0] $end
$var wire 8 3 PC_branch_address [7:0] $end
$var reg 8 4 PC [7:0] $end
$var reg 8 5 branch_offset [7:0] $end
$upscope $end
$scope module cu $end
$var wire 3 6 rt [2:0] $end
$var wire 3 7 rs [2:0] $end
$var wire 3 8 rd [2:0] $end
$var wire 4 9 opcode [3:0] $end
$var wire 16 : instruction [15:0] $end
$var wire 6 ; immidiate [5:0] $end
$var reg 3 < alu_op [2:0] $end
$var reg 1 = branch $end
$var reg 1 % reg_write $end
$var reg 1 & select_imm $end
$upscope $end
$scope module dp $end
$var wire 3 > alu_op [2:0] $end
$var wire 1 - carry $end
$var wire 1 ! clk $end
$var wire 6 ? immidiate [5:0] $end
$var wire 1 * overflow $end
$var wire 3 @ rd [2:0] $end
$var wire 1 % reg_write $end
$var wire 3 A rs [2:0] $end
$var wire 3 B rt [2:0] $end
$var wire 1 & select_imm $end
$var wire 1 $ zero $end
$var wire 8 C z [7:0] $end
$var wire 8 D x [7:0] $end
$var wire 8 E w [7:0] $end
$var wire 1 F alu_zero $end
$var wire 1 G alu_overflow $end
$var wire 1 H alu_carry $end
$var reg 8 I immidiate_8 [7:0] $end
$var reg 8 J y [7:0] $end
$scope module al $end
$var wire 8 K B [7:0] $end
$var wire 3 L alu_op [2:0] $end
$var wire 1 F zero $end
$var wire 1 G overflow $end
$var wire 1 H carry $end
$var wire 8 M A [7:0] $end
$var reg 8 N out_put [7:0] $end
$var reg 9 O temp_out [8:0] $end
$upscope $end
$scope module rf $end
$var wire 1 ! clk $end
$var wire 3 P rd [2:0] $end
$var wire 8 Q rd1 [7:0] $end
$var wire 8 R rd2 [7:0] $end
$var wire 3 S rs [2:0] $end
$var wire 3 T rt [2:0] $end
$var wire 8 U wd [7:0] $end
$var wire 1 % we $end
$var integer 32 V i [31:0] $end
$upscope $end
$upscope $end
$scope module instruction_memory $end
$var wire 8 W address [7:0] $end
$var wire 16 X instruction [15:0] $end
$upscope $end
$upscope $end
$upscope $end
$enddefinitions $end
$comment Show the parameter values. $end
$dumpall
$end
#0
$dumpvars
bx X
bx W
b1000 V
bx U
bx T
bx S
bx R
bx Q
bx P
bx O
bx N
bx M
bx L
bx K
bx J
bx I
xH
xG
xF
bx E
bx D
bx C
bx B
bx A
bx @
bx ?
bx >
x=
bx <
bx ;
bx :
bx 9
bx 8
bx 7
bx 6
bx 5
bx 4
bx 3
bx 2
bx 1
x0
bx /
bx .
x-
bx ,
bx +
x*
bx )
bx (
bx '
x&
x%
x$
z#
1"
0!
$end
#10000
0*
0G
00
b11110 J
b11110 K
0-
0H
0=
1&
1%
b0 .
b0 <
b0 >
b0 L
b11110 I
b111100 3
b11110 5
0$
0F
b11110 C
b11110 N
b11110 U
b11110 O
b1 )
b1 8
b1 @
b1 P
b1111 9
b11110 ,
b11110 1
b11110 ;
b11110 ?
b0 E
b0 R
b11 '
b11 6
b11 B
b11 T
b0 D
b0 M
b0 Q
b0 (
b0 7
b0 A
b0 S
b10 2
b1111001000011110 +
b1111001000011110 :
b1111001000011110 X
b0 /
b0 4
b0 W
1!
#20000
0!
#30000
1!
#40000
0!
0"
#50000
b10100 C
b10100 N
b10100 U
b10100 O
b10100 J
b10100 K
b10100 5
b10100 I
b10 )
b10 8
b10 @
b10 P
b10100 ,
b10100 1
b10100 ;
b10100 ?
b10 '
b10 6
b10 B
b10 T
b100 2
b101010 3
b1111010000010100 +
b1111010000010100 :
b1111010000010100 X
b10 /
b10 4
b10 W
1!
#60000
0!
#70000
0&
1%
b10000 I
b10000 5
b110010 C
b110010 N
b110010 U
b110010 O
b11 )
b11 8
b11 @
b11 P
b0 9
b10000 ,
b10000 1
b10000 ;
b10000 ?
b11110 D
b11110 M
b11110 Q
b1 (
b1 7
b1 A
b1 S
b10100 E
b10100 R
b110 2
b100100 3
b11001010000 +
b11001010000 :
b11001010000 X
b100 /
b100 4
b100 W
1!
#80000
0!
#90000
b1010 C
b1010 N
b1010 U
b1010 O
b1 .
b1 <
b1 >
b1 L
1%
b100 )
b100 8
b100 @
b100 P
b1 9
b1000 2
b100110 3
b1100001010000 +
b1100001010000 :
b1100001010000 X
b110 /
b110 4
b110 W
1!
#100000
0!
#110000
x*
xG
x0
x-
xH
0%
b0 .
b0 <
b0 >
b0 L
bx J
bx K
x$
xF
bx C
bx N
bx U
bx O
bx )
bx 8
bx @
bx P
bx 9
bx ,
bx 1
bx ;
bx ?
bx E
bx R
bx '
bx 6
bx B
bx T
bx D
bx M
bx Q
bx (
bx 7
bx A
bx S
b1010 2
b101000 3
bx +
bx :
bx X
b1000 /
b1000 4
b1000 W
1!
#120000
0!
#130000
b1100 2
b101010 3
b1010 /
b1010 4
b1010 W
1!
#140000
0!
#150000
b1110 2
b101100 3
b1100 /
b1100 4
b1100 W
1!
#160000
0!
#170000
b10000 2
b101110 3
b1110 /
b1110 4
b1110 W
1!
#180000
0!
#190000
b10010 2
b110000 3
b10000 /
b10000 4
b10000 W
1!
#200000
0!
#210000
b10100 2
b110010 3
b10010 /
b10010 4
b10010 W
1!
#220000
0!
#230000
b10110 2
b110100 3
b10100 /
b10100 4
b10100 W
1!
#240000
0!
#250000
b11000 2
b110110 3
b10110 /
b10110 4
b10110 W
1!
#260000
0!
#270000
b11010 2
b111000 3
b11000 /
b11000 4
b11000 W
1!
#280000
0!
#290000
b11100 2
b111010 3
b11010 /
b11010 4
b11010 W
1!
#300000
0!
#310000
b11110 2
b111100 3
b11100 /
b11100 4
b11100 W
1!
#320000
0!
#330000
b100000 2
b111110 3
b11110 /
b11110 4
b11110 W
1!
#340000
0!
#350000
b100010 2
b1000000 3
b100000 /
b100000 4
b100000 W
1!
#360000
0!
#370000
b100100 2
b1000010 3
b100010 /
b100010 4
b100010 W
1!
#380000
0!
#390000
b100110 2
b1000100 3
b100100 /
b100100 4
b100100 W
1!
#400000
0!
#410000
b101000 2
b1000110 3
b100110 /
b100110 4
b100110 W
1!
